aquatic/__init__.py
aquatic-0.0.0.dist-info/METADATA
aquatic-0.0.0.dist-info/WHEEL
aquatic-0.0.0.dist-info/top_level.txt
aquatic-0.0.0.dist-info/RECORD
