Metadata-Version: 2.1
Name: aquatic
Version: 0.0.0
Summary: A quantization-aware training library for PyTorch
Author: Sadique Sheik, Gregor Lenz
Author-email: sadique.sheik@synsense.ai
